<?xml version="1.0" standalone="yes"?>
<NewDataSet>
  <xs:schema id="NewDataSet" xmlns="" xmlns:xs="http://www.w3.org/2001/XMLSchema" xmlns:msdata="urn:schemas-microsoft-com:xml-msdata">
    <xs:element name="NewDataSet" msdata:IsDataSet="true" msdata:UseCurrentLocale="true">
      <xs:complexType>
        <xs:choice minOccurs="0" maxOccurs="unbounded">
          <xs:element name="Hosobenhan">
            <xs:complexType>
              <xs:sequence>
                <xs:element name="stt" type="xs:decimal" minOccurs="0" />  
                <xs:element name="mabn" type="xs:string" minOccurs="0" />               
                <xs:element name="hoten" type="xs:string" minOccurs="0" />               
                <xs:element name="nam" type="xs:string" minOccurs="0" />                           
                <xs:element name="nu" type="xs:string" minOccurs="0" />               
                <xs:element name="CVC" type="xs:string" minOccurs="0" />              
                <xs:element name="bhyt" type="xs:string" minOccurs="0" />    
                <xs:element name="Thanhthi" type="xs:string" minOccurs="0" />               
                <xs:element name="Nongthon" type="xs:string" minOccurs="0" />               
                <xs:element name="TEduoi12" type="xs:string" minOccurs="0" />               
                <xs:element name="TE1-15" type="xs:string" minOccurs="0" />               
                <xs:element name="nghenghiep" type="xs:string" minOccurs="0" />               
                <xs:element name="diachi" type="xs:string" minOccurs="0" />               
                <xs:element name="noigioithieu" type="xs:string" minOccurs="0" />               
                <xs:element name="vaovien" type="xs:string" minOccurs="0" />               
                <xs:element name="Chuyenvien" type="xs:string" minOccurs="0" />         
                <xs:element name="ravien" type="xs:string" minOccurs="0" />
                <xs:element name="tuvong" type="xs:string" minOccurs="0" />
                <xs:element name="tuvong24h" type="xs:string" minOccurs="0" />
                <xs:element name="CDGioithieu" type="xs:string" minOccurs="0" />
                <xs:element name="CDvao" type="xs:string" minOccurs="0" />
                <xs:element name="CDRA" type="xs:string" minOccurs="0" />
              </xs:sequence>
            </xs:complexType>
          </xs:element>
        </xs:choice>
      </xs:complexType>
    </xs:element>
  </xs:schema>
</NewDataSet>